{
  "title": "IMG_20241020_132408823_HDR.jpg",
  "description": "",
  "imageViews": "3",
  "creationTime": {
    "timestamp": "1746120123",
    "formatted": "May 1, 2025, 5:22:03 PM UTC"
  },
  "photoTakenTime": {
    "timestamp": "1729423449",
    "formatted": "Oct 20, 2024, 11:24:09 AM UTC"
  },
  "geoData": {
    "latitude": 51.063564,
    "longitude": 17.073161,
    "altitude": 164.0,
    "latitudeSpan": 0.0,
    "longitudeSpan": 0.0
  },
  "geoDataExif": {
    "latitude": 51.063564,
    "longitude": 17.073161,
    "altitude": 164.0,
    "latitudeSpan": 0.0,
    "longitudeSpan": 0.0
  },
  "url": "https://photos.google.com/photo/AF1QipPmUVsH68NpYMy86Gp0oaNmqgVKc5YRPmxBxNHs",
  "googlePhotosOrigin": {
    "mobileUpload": {
      "deviceFolder": {
        "localFolderName": ""
      },
      "deviceType": "ANDROID_PHONE"
    }
  },
  "appSource": {
    "androidPackageName": "com.motorola.camera3"
  }
}