{
  "title": "IMG_20241026_141816371.jpg",
  "description": "",
  "imageViews": "3",
  "creationTime": {
    "timestamp": "1746120123",
    "formatted": "May 1, 2025, 5:22:03 PM UTC"
  },
  "photoTakenTime": {
    "timestamp": "1729945096",
    "formatted": "Oct 26, 2024, 12:18:16 PM UTC"
  },
  "geoData": {
    "latitude": 51.075312,
    "longitude": 17.009933999999998,
    "altitude": 165.2,
    "latitudeSpan": 0.0,
    "longitudeSpan": 0.0
  },
  "geoDataExif": {
    "latitude": 51.075312,
    "longitude": 17.009933999999998,
    "altitude": 165.2,
    "latitudeSpan": 0.0,
    "longitudeSpan": 0.0
  },
  "url": "https://photos.google.com/photo/AF1QipPNMJ9sAp36ftRrN0s0_h6l0tQ4z3SBc0teXRec",
  "googlePhotosOrigin": {
    "mobileUpload": {
      "deviceFolder": {
        "localFolderName": ""
      },
      "deviceType": "ANDROID_PHONE"
    }
  },
  "appSource": {
    "androidPackageName": "com.motorola.camera3"
  }
}