{
  "title": "IMG_20240808_185630514_HDR.jpg",
  "description": "",
  "imageViews": "0",
  "creationTime": {
    "timestamp": "1746287517",
    "formatted": "May 3, 2025, 3:51:57 PM UTC"
  },
  "photoTakenTime": {
    "timestamp": "1723136191",
    "formatted": "Aug 8, 2024, 4:56:31 PM UTC"
  },
  "geoData": {
    "latitude": 43.871550000000006,
    "longitude": 10.241417,
    "altitude": 49.399,
    "latitudeSpan": 0.0,
    "longitudeSpan": 0.0
  },
  "geoDataExif": {
    "latitude": 43.871550000000006,
    "longitude": 10.241417,
    "altitude": 49.399,
    "latitudeSpan": 0.0,
    "longitudeSpan": 0.0
  },
  "url": "https://photos.google.com/photo/AF1QipNjgJTTotKwoP8E53YaOiIeHRVdzwlGOE8Spwtg",
  "googlePhotosOrigin": {
    "mobileUpload": {
      "deviceFolder": {
        "localFolderName": ""
      },
      "deviceType": "ANDROID_PHONE"
    }
  },
  "appSource": {
    "androidPackageName": "com.motorola.camera3"
  }
}